hive_library/__init__.py
hive_library/cli.py
hive_library/enum.py
hive_library/rest.py
hive_library-0.0.1b14.dist-info/LICENSE
hive_library-0.0.1b14.dist-info/METADATA
hive_library-0.0.1b14.dist-info/WHEEL
hive_library-0.0.1b14.dist-info/entry_points.txt
hive_library-0.0.1b14.dist-info/top_level.txt
hive_library-0.0.1b14.dist-info/RECORD
