Metadata-Version: 2.1
Name: hive-library
Version: 0.0.1b14
Summary: Python Hive Library
Home-page: https://hexway.io/
Author: HexWay
Author-email: contact@hexway.io
License: UNKNOWN
Platform: UNKNOWN
Classifier: Development Status :: 4 - Beta
Classifier: Environment :: Console
Classifier: Intended Audience :: Education
Classifier: License :: OSI Approved :: MIT License
Classifier: Natural Language :: English
Classifier: Operating System :: MacOS
Classifier: Operating System :: Microsoft :: Windows
Classifier: Operating System :: POSIX :: Linux
Classifier: Programming Language :: Python :: 3 :: Only
Classifier: Programming Language :: Python :: 3.6
Classifier: Programming Language :: Python :: 3.7
Classifier: Programming Language :: Python :: 3.8
Classifier: Programming Language :: Python :: 3.9
Classifier: Programming Language :: Python :: 3.10
Classifier: Topic :: Education
Classifier: Topic :: Security
Requires-Python: >=3.6
License-File: LICENSE
Requires-Dist: requests
Requires-Dist: urllib3
Requires-Dist: dataclasses
Requires-Dist: marshmallow
Requires-Dist: PyYAML
Requires-Dist: prettytable
